README.md
setup.py
php_formatter/__init__.py
php_formatter/main.py
php_formatter/formatter/__init__.py
php_formatter/formatter/_cases_creation.py
php_formatter/formatter/formatter.py
php_formatter/lexer/__init__.py
php_formatter/lexer/_char_checks.py
php_formatter/lexer/dict_token_types.py
php_formatter/lexer/lexer.py
php_formatter/lexer/token_classes.py
symphony_of_tranquility_php_formatter.egg-info/PKG-INFO
symphony_of_tranquility_php_formatter.egg-info/SOURCES.txt
symphony_of_tranquility_php_formatter.egg-info/dependency_links.txt
symphony_of_tranquility_php_formatter.egg-info/entry_points.txt
symphony_of_tranquility_php_formatter.egg-info/top_level.txt