Metadata-Version: 1.2
Name: symphony-of-tranquility-php-formatter
Version: 0.0.3
Summary: Php verifier and formatter
Home-page: UNKNOWN
Author: SymphonyOfTranquility
Author-email: symphony.of.tranquility@gmail.com
License: UNKNOWN
Platform: UNKNOWN
Requires-Python: >=3.6
